miniper-main/DePacketizer.v
module DePacketizer (
    input wire [47:0] flitoutde,  // Input is now 48 bits
    input wire clk,               // Main clock signal
    input wire reset,             // Reset signal
    output reg [15:0] data_out,   // Reconstructed output data
    output reg packet_end         // Packet end signal
);

reg flag;
reg [2:0]count;

    always @(posedge clk or posedge reset) begin
        if (reset) begin
            data_out <= 16'b0;
            packet_end <= 1'b0;
	    flag <= 1'b1;
            count <= 0;
        end else begin
            data_out <= flitoutde[31:16];
	    count <= 0;
  	    if((flitoutde[15:0] == 16'hFFFF) && flag)
	    begin
            packet_end <= 1'b1;
	    count <= count+1;
	    flag <= 1'b0;
	    end 

            else 
	    packet_end <= 1'b0;
            
            if(count > 0)
	    flag <= 1'b1;
        end
    end
endmodule

miniper-main/DePacketizer_tb.v
module DePacketizer_tb;

reg clk;
reg reset;
reg [47:0] flitoutde;

wire [15:0] data_out;
wire packet_end;

DePacketizer dut(.clk(clk), .reset(reset), .flitoutde(flitoutde), .data_out(data_out), .packet_end(packet_end));

initial
   begin
	   clk = 0;
	end
	
always #5 clk = ~clk;

initial
   begin
	  reset = 1;
	  #10;
	  reset = 0;
	  #10;
	  flitoutde = 48'h1234_ABCD_FFFF;
	  #20;
	  flitoutde = 48'h3232_6767_FFFF;
	  #20;
	  flitoutde = 48'h6547_4576_FFFF;
          #40;
	  flitoutde = 48'h6969_4566_FFFF;
    	  #30;

	  $finish;
	end

initial 
begin 
	$dumpfile("dump.vcd");
	$dumpvars();
end 
	
endmodule

miniper-main/dump.vcd
$date
	Thu Nov 21 14:01:26 2024
$end

$version
	Synopsys VCS version U-2023.03
$end

$timescale
	1s
$end

$comment Csum: 1 41617324233dbfc1 $end


$scope module DePacketizer_tb $end
$var reg 1 ! clk $end
$var reg 1 " reset $end
$var reg 48 # flitoutde [47:0] $end
$var wire 16 $ data_out [15:0] $end
$var wire 1 % packet_end $end

$scope module dut $end
$var wire 48 # flitoutde [47:0] $end
$var wire 1 ! clk $end
$var wire 1 " reset $end
$var reg 16 $ data_out [15:0] $end
$var reg 1 % packet_end $end
$var reg 1 & flag $end
$var reg 3 ' count [2:0] $end
$upscope $end

$upscope $end

$enddefinitions $end

#0
$dumpvars
0!
0%
1&
1"
b000 '
b0000000000000000 $
bxxxxxxxxxxxxxxxxxxxxxxxxxxxxxxxxxxxxxxxxxxxxxxxx #
$end
#5
1!
#10
0"
0!
#15
1!
bxxxxxxxxxxxxxxxx $
#20
b000100100011010010101011110011011111111111111111 #
0!
#25
1!
b1010101111001101 $
b001 '
1%
0&
#30
0!
#35
1!
b000 '
0%
1&
#40
b001100100011001001100111011001111111111111111111 #
0!
#45
1!
b0110011101100111 $
b001 '
1%
0&
#50
0!
#55
1!
b000 '
0%
1&
#60
b011001010100011101000101011101101111111111111111 #
0!
#65
1!
b0100010101110110 $
b001 '
1%
0&
#70
0!
#75
1!
b000 '
0%
1&
#80
0!
#85
1!
b001 '
1%
0&
#90
0!
#95
1!
b000 '
0%
1&
#100
b011010010110100101000101011001101111111111111111 #
0!
#105
1!
b0100010101100110 $
b001 '
1%
0&
#110
0!
#115
1!
b000 '
0%
1&
#120
0!
#125
1!
b001 '
1%
0&
